<annotation>
	<folder>images</folder>
	<filename>82.jpg</filename>
	<path>C:/Users/yx/Desktop/CCF/apple_dataset/新建文件夹/images/82.jpg</path>
	<source>
		<database>Unknown</database>
	</source>
	<size>
		<width>313</width>
		<height>209</height>
		<depth>3</depth>
	</size>
	<segmented>0</segmented>
	<object>
		<name>apple</name>
		<pose>Unspecified</pose>
		<truncated>0</truncated>
		<difficult>0</difficult>
		<bndbox>
			<xmin>144</xmin>
			<ymin>26</ymin>
			<xmax>237</xmax>
			<ymax>115</ymax>
		</bndbox>
	</object>
	<object>
		<name>obscured(0)_apple</name>
		<pose>Unspecified</pose>
		<truncated>0</truncated>
		<difficult>0</difficult>
		<bndbox>
			<xmin>97</xmin>
			<ymin>92</ymin>
			<xmax>184</xmax>
			<ymax>186</ymax>
		</bndbox>
	</object>
	<object>
		<name>obscured(2)_apple</name>
		<pose>Unspecified</pose>
		<truncated>0</truncated>
		<difficult>0</difficult>
		<bndbox>
			<xmin>179</xmin>
			<ymin>95</ymin>
			<xmax>259</xmax>
			<ymax>187</ymax>
		</bndbox>
	</object>
</annotation>
